[{"CustomerNo":1105,"Memo":"DO NOT SHIP HOLLAND"},{"CustomerNo":1161,"Memo":"DO NOT SHIP FEDEX; NO WED DELV"},{"CustomerNo":2323,"Memo":"DO NOT SHIP UPS FRT"},{"CustomerNo":2413,"Memo":"DO NOT USE DORHN OR SUTTON"},{"CustomerNo":2413,"Memo":"DO NOT USE DORHN OR SUTTON"},{"CustomerNo":2413,"Memo":"collect UPS FRT OR FED EX FRT ONLY"},{"CustomerNo":3056,"Memo":"Do not ship Standard Forwardin"},{"CustomerNo":3463,"Memo":"DO NOT SHIP HOLLAND!"},{"CustomerNo":3463,"Memo":"DO NOT SHIP HOLLAND!"},{"CustomerNo":3520,"Memo":"DO NOT SHIP FED EX FRT"},{"CustomerNo":4120,"Memo":"DO NOT SHIP UPS FREIGHT"},{"CustomerNo":4132,"Memo":"NO FED EX FREIGHT"},{"CustomerNo":4255,"Memo":"NO UPS FRT"},{"CustomerNo":4402,"Memo":"NO UPS FRT"},{"CustomerNo":4897,"Memo":"DO NOT USE FED EX FRT"},{"CustomerNo":4897,"Memo":"DO NOT USE FED EX FRT"},{"CustomerNo":4897,"Memo":"DO NOT USE CUSTOM CO"},{"CustomerNo":5805,"Memo":"NO FED EX FRT"},{"CustomerNo":5810,"Memo":"USE ESTES OR AVERRIT "},{"CustomerNo":5816,"Memo":"DO NOT SHIP YRC"},{"CustomerNo":7145,"Memo":"DO NOT USE UPS FRT"},{"CustomerNo":10058,"Memo":"DO NOT SHIP UPS FRT"},{"CustomerNo":10150,"Memo":"NO UPS FREIGHT"},{"CustomerNo":20156,"Memo":"DO NOT SHIP AVERITT EXPRESS"},{"CustomerNo":20156,"Memo":"DO NOT SHIP AVERITT EXPRESS"},{"CustomerNo":20156,"Memo":"DO NOT SHIP AVERITT EXPRESS"},{"CustomerNo":20180,"Memo":"DO NOT SHIP HOLLAND"},{"CustomerNo":20252,"Memo":"DO NOT SHIP W\/ AVERITT"},{"CustomerNo":20252,"Memo":"DO NOT SHIP W\/ AVERITT"},{"CustomerNo":20252,"Memo":"DO NOT SHIP W\/ AVERITT"},{"CustomerNo":20252,"Memo":"DO NOT SHIP W\/ AVERITT"},{"CustomerNo":20252,"Memo":"DO NOT SHIP W\/ AVERITT"},{"CustomerNo":20252,"Memo":"DO NOT SHIP W\/ AVERITT"},{"CustomerNo":20252,"Memo":"DO NOT SHIP W\/ AVERITT"},{"CustomerNo":20252,"Memo":"DO NOT SHIP W\/ AVERITT"},{"CustomerNo":20252,"Memo":"DO NOT SHIP W\/ AVERITT"},{"CustomerNo":20252,"Memo":"DO NOT SHIP W\/ AVERITT"},{"CustomerNo":20252,"Memo":"DO NOT SHIP W\/ AVERITT"},{"CustomerNo":20252,"Memo":"DO NOT SHIP W\/ AVERITT"},{"CustomerNo":20252,"Memo":"DO NOT SHIP W\/ AVERITT"},{"CustomerNo":20252,"Memo":"DO NOT SHIP W\/ AVERITT"},{"CustomerNo":20252,"Memo":"DO NOT SHIP W\/ AVERITT"},{"CustomerNo":20256,"Memo":"DO NOT SHIP XPO LOGISTICS"},{"CustomerNo":2386,"Memo":"DO NOT SHIP XPO LOGISTICS"},{"CustomerNo":2410,"Memo":"DO NOT USE CUSTOM CO"},{"CustomerNo":2413,"Memo":"DO NOT USE DORHN OR SUTTON"},{"CustomerNo":3052,"Memo":"SHIP XPO"},{"CustomerNo":4132,"Memo":"DO NOT SHIP FEDEX FREIGHT"},{"CustomerNo":4897,"Memo":"DO NOT USE CUSTOM CO"},{"CustomerNo":4913,"Memo":"DO NOT USE UPS FREIGHT"},{"CustomerNo":9151,"Memo":"DO NOT USE DOHRN "},{"CustomerNo":9471,"Memo":"USE SAIA"},{"CustomerNo":9528,"Memo":"USE SAIA"},{"CustomerNo":10090,"Memo":"DO NOT USE UPS FREIGHT"},{"CustomerNo":20256,"Memo":"DO NOT SHIP XPO LOGISTICS"}]